hf_dataset_selector-0.2.1.dist-info/licenses/LICENSE
hfselect/__init__.py
hfselect/dataset.py
hfselect/embedding_dataset.py
hfselect/esm.py
hfselect/esm_logme.py
hfselect/esmconfig.py
hfselect/logme.py
hfselect/logme_self_implemented.py
hfselect/model_utils.py
hfselect/setup_logger.py
hfselect/task_ranking.py
hfselect/trainers.py
hfselect/utils.py
hfselect/version.py
hf_dataset_selector-0.2.1.dist-info/METADATA
hf_dataset_selector-0.2.1.dist-info/WHEEL
hf_dataset_selector-0.2.1.dist-info/top_level.txt
hf_dataset_selector-0.2.1.dist-info/RECORD
