Metadata-Version: 2.4
Name: hf-dataset-selector
Version: 0.2.1
Summary: A convenient and fast Python package to find the best datasets for intermediate fine-tuning for your task.
Author-email: David Schulte <davidsiriusschulte@gmail.com>
License:                                  Apache License
Requires-Python: >=3.11
License-File: LICENSE
Requires-Dist: datasets>=3.2.0
Requires-Dist: huggingface-hub>=0.27.0
Requires-Dist: numba>=0.60.0
Requires-Dist: numpy==2.0.0
Requires-Dist: pandas>=2.2.3
Requires-Dist: torch>=2.5.1
Requires-Dist: tqdm>=4.67.1
Requires-Dist: transformers>=4.48.0
Dynamic: license-file
